nbcleanse/__init__.py
nbcleanse/_modidx.py
nbcleanse/_nbdev.py
nbcleanse/cli.py
nbcleanse/notebook.py
nbcleanse-0.0.3.dist-info/LICENSE
nbcleanse-0.0.3.dist-info/METADATA
nbcleanse-0.0.3.dist-info/WHEEL
nbcleanse-0.0.3.dist-info/entry_points.txt
nbcleanse-0.0.3.dist-info/top_level.txt
nbcleanse-0.0.3.dist-info/RECORD
