Metadata-Version: 2.1
Name: nbcleanse
Version: 0.0.3
Summary: A library for cleaning jupyter notebooks real good
Home-page: https://github.com/shacharhelmer/nbcleanse/
Author: shachar helmer
Author-email: shachar.helmer@gmail.com
License: Apache Software License 2.0
Keywords: jupyter,notebook,clean,clean notebook,clean jupyter notebook
Classifier: Development Status :: 3 - Alpha
Classifier: Intended Audience :: Developers
Classifier: Natural Language :: English
Classifier: Programming Language :: Python :: 3.7
Classifier: Programming Language :: Python :: 3.8
Classifier: Programming Language :: Python :: 3.9
Classifier: Programming Language :: Python :: 3.10
Classifier: License :: OSI Approved :: Apache Software License
Requires-Python: >=3.7
License-File: LICENSE
Requires-Dist: jq
Requires-Dist: nbformat
Provides-Extra: dev
